chroma_helper_module/__init__.py
chroma_helper_module/chroma_helper_module.py
my_chroma_helper-0.1.0.dist-info/METADATA
my_chroma_helper-0.1.0.dist-info/WHEEL
my_chroma_helper-0.1.0.dist-info/top_level.txt
my_chroma_helper-0.1.0.dist-info/RECORD
